ses_mailer.py
SES_Mailer_2-0.14.2.dist-info/DESCRIPTION.rst
SES_Mailer_2-0.14.2.dist-info/METADATA
SES_Mailer_2-0.14.2.dist-info/RECORD
SES_Mailer_2-0.14.2.dist-info/WHEEL
SES_Mailer_2-0.14.2.dist-info/metadata.json
SES_Mailer_2-0.14.2.dist-info/top_level.txt
