Metadata-Version: 2.0
Name: SES-Mailer-2
Version: 0.14.2
Summary: A simple module to send email via AWS SES
Home-page: http://github.com/MarSoft/ses-mailer-2/
Author: Mardix
Author-email: mardix@github.com
License: MIT
Download-URL: http://github.com/MarSoft/ses-mailer-2/tarball/master
Keywords: email,flask,aws ses,amazon,ses,mailer,jinja2,template email
Platform: any
Classifier: Environment :: Web Environment
Classifier: Intended Audience :: Developers
Classifier: License :: OSI Approved :: BSD License
Classifier: Operating System :: OS Independent
Classifier: Programming Language :: Python
Classifier: Programming Language :: Python :: 2
Classifier: Programming Language :: Python :: 2.6
Classifier: Programming Language :: Python :: 2.7
Classifier: Programming Language :: Python :: 3
Classifier: Programming Language :: Python :: 3.3
Classifier: Topic :: Internet :: WWW/HTTP :: Dynamic Content
Classifier: Topic :: Software Development :: Libraries :: Python Modules
Requires-Dist: boto
Requires-Dist: jinja2
